devpi_builder/__init__.py
devpi_builder/cli.py
devpi_builder/requirements.py
devpi_builder/wheeler.py
devpi_builder-6.1.0.dist-info/COPYING
devpi_builder-6.1.0.dist-info/METADATA
devpi_builder-6.1.0.dist-info/WHEEL
devpi_builder-6.1.0.dist-info/entry_points.txt
devpi_builder-6.1.0.dist-info/top_level.txt
devpi_builder-6.1.0.dist-info/RECORD
