Metadata-Version: 2.1
Name: devpi-builder
Version: 6.1.0
Summary: Devpi-builder takes a requirements.txt and incrementally fills a devpi index with wheels of the listed python packages.
Home-page: https://github.com/blue-yonder/devpi-builder
Author: Matthias Bach
Author-email: matthias.bach@blue-yonder.com
License: new BSD
Classifier: Development Status :: 5 - Production/Stable
Classifier: Environment :: Console
Classifier: Intended Audience :: Developers
Classifier: Intended Audience :: System Administrators
Classifier: License :: OSI Approved :: BSD License
Classifier: Topic :: System :: Archiving :: Packaging
Classifier: Programming Language :: Python :: 3
Classifier: Programming Language :: Python :: 3.7
Classifier: Programming Language :: Python :: 3.8
Classifier: Programming Language :: Python :: 3.9
Classifier: Programming Language :: Python :: 3.10
Classifier: Programming Language :: Python :: 3.11
Requires-Python: >=3.7
License-File: COPYING
Requires-Dist: devpi-plumber >=0.2.14
Requires-Dist: setuptools
Requires-Dist: wheel
Requires-Dist: wheel-filename
Requires-Dist: wheel-inspect >=1.6.0
Requires-Dist: pip >=1.5.3
Requires-Dist: junit-xml
Requires-Dist: pip-requirements-parser >=32.0.1
